apicore
tests
